wagtail_non_admin_draftail/__init__.py
wagtail_non_admin_draftail/apps.py
wagtail_non_admin_draftail/conf.py
wagtail_non_admin_draftail/forms.py
wagtail_non_admin_draftail/static/wagtail_non_admin_draftail/draftail.css
wagtail_non_admin_draftail/static/wagtail_non_admin_draftail/draftail.css.map
wagtail_non_admin_draftail/static/wagtail_non_admin_draftail/modal-workflow.js
wagtail_non_admin_draftail/static_src/.gitignore
wagtail_non_admin_draftail/static_src/README.md
wagtail_non_admin_draftail/static_src/package-lock.json
wagtail_non_admin_draftail/static_src/package.json
wagtail_non_admin_draftail/static_src/src/index.scss
wagtail_non_admin_draftail/static_src/src/styles/chooser.scss
wagtail_non_admin_draftail/static_src/src/styles/editor.scss
wagtail_non_admin_draftail/static_src/src/styles/modal.scss
wagtail_non_admin_draftail/static_src/src/styles/tooltip.scss
wagtail_non_admin_draftail/templates/wagtail_non_admin_draftail/_draftail_css.html
wagtail_non_admin_draftail/templates/wagtail_non_admin_draftail/_draftail_js.html
wagtail_non_admin_draftail/templates/wagtail_non_admin_draftail/document/upload.html
wagtail_non_admin_draftail/templates/wagtail_non_admin_draftail/draftail_media.html
wagtail_non_admin_draftail/templates/wagtail_non_admin_draftail/embed/chooser.html
wagtail_non_admin_draftail/templates/wagtail_non_admin_draftail/image/select_format.html
wagtail_non_admin_draftail/templates/wagtail_non_admin_draftail/image/upload.html
wagtail_non_admin_draftail/templates/wagtail_non_admin_draftail/link/_link_types.html
wagtail_non_admin_draftail/templates/wagtail_non_admin_draftail/link/anchor_link.html
wagtail_non_admin_draftail/templates/wagtail_non_admin_draftail/link/email_link.html
wagtail_non_admin_draftail/templates/wagtail_non_admin_draftail/link/external_link.html
wagtail_non_admin_draftail/templates/wagtail_non_admin_draftail/link/phone_link.html
wagtail_non_admin_draftail/templates/wagtail_non_admin_draftail/modal_base.html
wagtail_non_admin_draftail-0.20.0.dist-info/LICENSE
wagtail_non_admin_draftail-0.20.0.dist-info/METADATA
wagtail_non_admin_draftail-0.20.0.dist-info/WHEEL
wagtail_non_admin_draftail-0.20.0.dist-info/RECORD
