Metadata-Version: 2.3
Name: wagtail_non_admin_draftail
Version: 0.20.0
Summary: You can now use Wagtail Draftail editor on non-admin pages
License: MIT
Author: Tim Kamanin
Author-email: tim@timonweb.com
Requires-Python: >=3.10.0,<4.0.0
Classifier: License :: OSI Approved :: MIT License
Classifier: Programming Language :: Python :: 3
Classifier: Programming Language :: Python :: 3.10
Classifier: Programming Language :: Python :: 3.11
Classifier: Programming Language :: Python :: 3.12
Classifier: Programming Language :: Python :: 3.13
Requires-Dist: wagtail (>=7.0.1,<8.0.0)
Project-URL: Homepage, https://timonweb.com
Project-URL: Repository, https://github.com/timonweb/wagtail-non-admin-draftail
